[{"id":"c5f0e750-0166-46ba-b8f9-b2ad8e4a58d0","item":"bournvita","selling_price":20,"cost_price":30,"qty":5,"expiring_date":"22-13-2008","alert_date":"3-13-2019"},{"id":"c5f0e750-0166-46bb-b8f9-b2ad8e4a58d0","item":"tea","selling_price":500,"cost_price":400,"qty":55,"expiring_date":"22-13-2008","alert_date":"22-13-2008"},{"id":"c5f0e750-0166-46ba-b8g9-b2ad8e4a58d0","item":"klin","selling_price":30,"cost_price":300,"qty":640,"expiring_date":"22-13-2008","alert_date":"22-13-2008"},{"id":"c5f0e750-0166-46bc-b8f9-b2ad8e4a58d0","item":"noy","selling_price":76,"cost_price":67,"qty":50,"expiring_date":"22-13-2008","alert_date":"22-13-2008"},{"id":"c5f0e750-0166-46ba-b8f9-b2ac8e4a58d0","item":"victor","selling_price":60,"cost_price":90,"qty":80,"expiring_date":"22-13-2008","alert_date":"22-13-2008"},{"item":"tyu","selling_price":4545,"cost_price":4545,"qty":0,"expiring_date":"22/11/2000","alert_date":"22/11/2000","id":"20357ad5-d6db-41b7-88e9-37678ab4e9dc"},{"item":"noy","selling_price":9867,"cost_price":656,"qty":0,"expiring_date":"22/11/2000","alert_date":"22/11/2000","id":"8457cf5d-32a7-4d4f-a672-4434b9192efe"},{"item":"noyuy","selling_price":9867,"cost_price":656,"qty":0,"expiring_date":"22/11/2000","alert_date":"22/11/2000","id":"d02277c3-7c34-4794-8a58-a8d95855a132"}]